excel_mcp/__init__.py
excel_mcp/__main__.py
excel_mcp/calculations.py
excel_mcp/cell_utils.py
excel_mcp/cell_validation.py
excel_mcp/chart.py
excel_mcp/data.py
excel_mcp/exceptions.py
excel_mcp/formatting.py
excel_mcp/pivot.py
excel_mcp/server.py
excel_mcp/sheet.py
excel_mcp/tables.py
excel_mcp/validation.py
excel_mcp/workbook.py
mcp_excel_tools-0.1.9.dist-info/METADATA
mcp_excel_tools-0.1.9.dist-info/WHEEL
mcp_excel_tools-0.1.9.dist-info/entry_points.txt
mcp_excel_tools-0.1.9.dist-info/licenses/LICENSE
mcp_excel_tools-0.1.9.dist-info/RECORD
